aissemble_open_inference_protocol_fastapi/__init__.py
aissemble_open_inference_protocol_fastapi/aissemble_oip_fastapi.py
aissemble_open_inference_protocol_fastapi/rest/__init__.py
aissemble_open_inference_protocol_fastapi/rest/endpoints.py
aissemble_open_inference_protocol_fastapi-1.1.0.dist-info/METADATA
aissemble_open_inference_protocol_fastapi-1.1.0.dist-info/WHEEL
aissemble_open_inference_protocol_fastapi-1.1.0.dist-info/licenses/LICENSE.txt
aissemble_open_inference_protocol_fastapi-1.1.0.dist-info/RECORD
